_version.py
find_duplicates.py
restore_exif.py
whatsapp_media_tools-0.1.2.dist-info/METADATA
whatsapp_media_tools-0.1.2.dist-info/WHEEL
whatsapp_media_tools-0.1.2.dist-info/entry_points.txt
whatsapp_media_tools-0.1.2.dist-info/top_level.txt
whatsapp_media_tools-0.1.2.dist-info/RECORD
