Metadata-Version: 2.1
Name: whatsapp-media-tools
Version: 0.1.2
Summary: Python scripts to manage WhatsApp media backups for archival purposes
Author-email: Alain Girard <alaingirardvd@gmail.com>
Project-URL: Homepage, https://github.com/Allain18/whatsapp-media-tools
Keywords: whatsapp,EXIF,image
Classifier: Development Status :: 4 - Beta
Classifier: Intended Audience :: Developers
Classifier: License :: OSI Approved :: MIT License
Classifier: Natural Language :: English
Classifier: Programming Language :: Python :: 3.6
Classifier: Programming Language :: Python :: 3.7
Classifier: Programming Language :: Python :: 3.8
Classifier: Programming Language :: Python :: 3.9
Classifier: Programming Language :: Python :: 3.10
Classifier: Programming Language :: Python :: Implementation :: PyPy
Classifier: Environment :: Console
Classifier: Operating System :: OS Independent
Requires-Python: >=3.6
Requires-Dist: piexif (>=1.1.3)
